{
    "CHARAbbrev.WS": "KG",
	"CHARAbbrev.BS": "BF",
	"CHARAbbrev.S": "S",
	"CHARAbbrev.T": "WI",
	"CHARAbbrev.I": "I",
	"CHARAbbrev.Ag": "GW",
	"CHARAbbrev.Dex": "GS",
	"CHARAbbrev.Int": "IN",
	"CHARAbbrev.WP": "WK",
    "CHARAbbrev.Fel": "CH",

    "CHARBonus.WS": "Kampfgeschick Bonus",
	"CHARBonus.BS": "Ballistische Fertigkeit Bonus",
	"CHARBonus.S": "Stärke Bonus",
	"CHARBonus.T": "Widerstand Bonus",
	"CHARBonus.I": "Initiative Bonus",
	"CHARBonus.Ag": "Gewandheit Bonus",
	"CHARBonus.Dex": "Geschicklichkeit Bonus",
	"CHARBonus.Int": "Intelligenz Bonus",
	"CHARBonus.WP": "Willenskraft Bonus",
    "CHARBonus.Fel": "Charisma Bonus",
    "Bonus" : "Bonus",

    "NAME.Armour" : "Rüstung",
    "NAME.Hardy" : "Robustheit",
    "NAME.Small" : "Zierlich",
    "NAME.Mindless" : "Geistlos",
    "NAME.Construct" : "Konstrukt",
    "NAME.Swarm" : "Schwarm",
    "NAME.Size" : "Größe",
    "SPEC.Tiny" : "Winzig",
    "SPEC.Little" : "Klein",
    "SPEC.Small" : "Zierlich",
    "SPEC.Average" : "Normal",
    "SPEC.Large" : "Groß",
    "SPEC.Enormous" : "Enorm",
    "SPEC.Monstrous" : "Monströs",

    "NAME.BP" : "Messinggroschen",
    "NAME.SS" : "Silberschilling",
    "NAME.GC" : "Goldkrone",

    "NAME.BPPlural" : "Messinggroschen",
    "NAME.SSPlural" : "Silberschillinge",
    "NAME.GCPlural" : "Goldkronen",

    "TIER.Gold" : "Gold",
    "TIER.Silver" : "Silber",
    "TIER.Brass" : "Messing"
	
	"NAME.Pray" : "Beten",
    "NAME.Language" : "Sprache",
    "SPEC.Magick" : "Magick",
    "NAME.Channelling" : "Kanalisieren",
    "NAME.Melee" : "Nahkampf",
    "NAME.Ranged" : "Fernkampf",
    "NAME.Endurance" : "Ausdauer",
    "NAME.Cool" : "Besonnenheit",
    "NAME.Dodge" : "Ausweichen",
    "NAME.Stride" : "Geschwind",
    "NAME.Unarmed" : "Waffenlos",
    "NAME.Stomp" : "Niedertrampeln",
    "NAME.Improvised" : "Improvisierte Waffe",
    "NAME.ID" : "Instinktive Aussprache",
    "NAME.AA" : "Äthergespür",
    "NAME.SMB" : "Mächtiger Schlag",
    "NAME.AS" : "Zielsicherheit",
    "NAME.Robust" : "Hart im Nehmen",
    "NAME.PS" : "Reine Seele",
    "NAME.StrongBack" : "Starker Rücken",
    "NAME.Sturdy" : "Stämmig",
    "NAME.ConsumeAlcohol" : "Trunkenbold",
    "NAME.Stealth" : "Schleichen",
    "NAME.PickLock" : "Schlösser öffnen",
    "NAME.Champion" : "Champion",
    "NAME.Riposte" : "Riposte",
    "NAME.Ambi" : "Beidhändigkeit",
    "NAME.Resolute" : "Entschlossen",
    "NAME.DualWielder" : "Beidhändiger Kampf",
    "NAME.Trickriding" : "Kunstreiter",
    "NAME.Corruption" : "Korruption",
    "NAME.Infected" : "Infiziert",
    "NAME.Disease" : "Krankheit",
    "NAME.Daemonic" : "Dämonisch",
    "NAME.Slayer" : "Slayer"
}
